dectime/__init__.py
dectime-0.3.3.dist-info/AUTHORS.rst
dectime-0.3.3.dist-info/LICENSE.txt
dectime-0.3.3.dist-info/METADATA
dectime-0.3.3.dist-info/WHEEL
dectime-0.3.3.dist-info/entry_points.txt
dectime-0.3.3.dist-info/top_level.txt
dectime-0.3.3.dist-info/RECORD
