Metadata-Version: 2.1
Name: dectime
Version: 0.3.3
Summary: Decimal time cli.
Author-email: allan bailey <zirpubolci@gmail.com>
License: The MIT License (MIT)        
Project-URL: repository, https://git.sr.ht/~zirpu/dectime
Keywords: cli
Classifier: License :: OSI Approved :: MIT License
Classifier: Programming Language :: Python
Classifier: Programming Language :: Python :: 3
Requires-Python: >=3.9
License-File: LICENSE.txt
License-File: AUTHORS.rst
Requires-Dist: colorama (>=0.4.4)
Requires-Dist: python-baseconv (>=1.2.2)
